vistafetch/__init__.py
vistafetch/client.py
vistafetch/constants.py
vistafetch/logs.py
vistafetch/py.typed
vistafetch/session.py
vistafetch/model/__init__.py
vistafetch/model/base.py
vistafetch/model/search_result.py
vistafetch/model/asset/__init__.py
vistafetch/model/asset/bond.py
vistafetch/model/asset/derivative.py
vistafetch/model/asset/financial_asset.py
vistafetch/model/asset/financial_asset_type.py
vistafetch/model/asset/financial_data.py
vistafetch/model/asset/fund.py
vistafetch/model/asset/index.py
vistafetch/model/asset/metal.py
vistafetch/model/asset/stock.py
vistafetch-2.1.1.dist-info/licenses/LICENSE
vistafetch-2.1.1.dist-info/METADATA
vistafetch-2.1.1.dist-info/WHEEL
vistafetch-2.1.1.dist-info/top_level.txt
vistafetch-2.1.1.dist-info/RECORD
