Metadata-Version: 2.4
Name: vistafetch
Version: 2.1.1
Summary: Small & simple library to fetch financial data for stocks, ETFs, funds, etc. from Onvista.
Author-email: bossenti <bossenti@apache.org>
License: Apache 2.0
Project-URL: homepage, https://github.com/bossenti/vistafetch
Project-URL: documentation, https://github.com/bossenti/vistafetch/blob/main/README.md
Project-URL: repository, https://github.com/bossenti/vistafetch
Project-URL: changelog, https://github.com/bossenti/vistafetch/releases
Keywords: etf,exchange,financial-data,funds,onvista,stocks
Classifier: Development Status :: 4 - Beta
Classifier: Environment :: Console
Classifier: Framework :: Pydantic :: 2
Classifier: Intended Audience :: Developers
Classifier: Intended Audience :: Financial and Insurance Industry
Classifier: Intended Audience :: Science/Research
Classifier: License :: OSI Approved :: Apache Software License
Classifier: Operating System :: OS Independent
Classifier: Topic :: Office/Business :: Financial :: Investment
Classifier: Programming Language :: Python :: 3.9
Classifier: Programming Language :: Python :: 3.10
Classifier: Programming Language :: Python :: 3.11
Classifier: Programming Language :: Python :: 3.12
Classifier: Programming Language :: Python :: 3.13
Requires-Python: <3.14,>=3.9
License-File: LICENSE
Requires-Dist: pydantic>=2.0.0
Requires-Dist: requests>=2.31.0
Requires-Dist: rich>=13.0.0
Dynamic: license-file
